amds/__init__.py
amds/_hooks/__init__.py
amds/_hooks/registration.py
amds/_hooks/sdkhooks.py
amds/_hooks/types.py
amds/_version.py
amds/alph.py
amds/basesdk.py
amds/cli/__init__.py
amds/cli/commands/README.md
amds/cli/commands/alph.py
amds/cli/commands/compute.py
amds/cli/commands/environments.py
amds/cli/commands/login.py
amds/cli/commands/servers.py
amds/cli/main.py
amds/cli/utils.py
amds/compute.py
amds/environments.py
amds/files.py
amds/httpclient.py
amds/integratedservers.py
amds/models/__init__.py
amds/models/addintegratedserverop.py
amds/models/apierror.py
amds/models/claude35haikuop.py
amds/models/claude35sonnetop.py
amds/models/createserverop.py
amds/models/createtunnelop.py
amds/models/deleteintegratedserverop.py
amds/models/deleteserverop.py
amds/models/deletetunnelop.py
amds/models/getcomputeop.py
amds/models/getenvironmentsop.py
amds/models/getfileop.py
amds/models/getintegratedserversop.py
amds/models/getserversop.py
amds/models/gettunnelop.py
amds/models/gpt4ominiop.py
amds/models/gpt4oop.py
amds/models/gpt4op.py
amds/models/runcodeop.py
amds/models/security.py
amds/models/startserverop.py
amds/models/stopserverop.py
amds/models/uploadfileop.py
amds/py.typed
amds/sdk.py
amds/sdkconfiguration.py
amds/servers.py
amds/tunnels.py
amds/types/__init__.py
amds/types/basemodel.py
amds/utils/__init__.py
amds/utils/annotations.py
amds/utils/enums.py
amds/utils/eventstreaming.py
amds/utils/forms.py
amds/utils/headers.py
amds/utils/logger.py
amds/utils/metadata.py
amds/utils/queryparams.py
amds/utils/requestbodies.py
amds/utils/retries.py
amds/utils/security.py
amds/utils/serializers.py
amds/utils/url.py
amds/utils/values.py
amds-0.5.24.dist-info/METADATA
amds-0.5.24.dist-info/WHEEL
amds-0.5.24.dist-info/entry_points.txt
amds-0.5.24.dist-info/RECORD
