Metadata-Version: 2.3
Name: amds
Version: 0.5.24
Summary: American Data Science Python SDK and CLI
Author: Andrew Chang
Requires-Python: >=3.9
Classifier: Programming Language :: Python :: 3
Classifier: Programming Language :: Python :: 3.9
Classifier: Programming Language :: Python :: 3.10
Classifier: Programming Language :: Python :: 3.11
Classifier: Programming Language :: Python :: 3.12
Classifier: Programming Language :: Python :: 3.13
Requires-Dist: click (>=8.1.8,<9.0.0)
Requires-Dist: eval-type-backport (>=0.2.0)
Requires-Dist: httpx (>=0.28.1)
Requires-Dist: jupyterlab (>=4.3.5,<5.0.0)
Requires-Dist: pydantic (>=2.10.3)
Requires-Dist: python-dateutil (>=2.8.2)
Requires-Dist: types-requests (>=2.32.0,<3.0.0)
Requires-Dist: typing-inspection (>=0.4.0)
Project-URL: Repository, https://github.com/americandatascience/amds.git
